{
  "users": [
    {
      "id": "1",
      "username": "jassim_cartify",
      "password": "123",
      "email": "jassim_cartify@email.com",
      "phone": "0902121",
      "isAdmin": false,
      "cart": [],
      "pendingOrders": [],
      "firstName": "",
      "middleName": "",
      "lastName": "",
      "birthDate": "2024-09-11",
      "interest": "",
      "status": "Active"
    },
    {
      "id": "2",
      "username": "jeff_cartify",
      "password": "123",
      "email": "jeff_cartify@gmail.com",
      "phone": "0902121",
      "isAdmin": false,
      "cart": [],
      "pendingOrders": [],
      "firstName": "",
      "middleName": "",
      "lastName": "",
      "birthDate": "2024-09-11",
      "interest": "",
      "status": "Active"
    },
    {
      "id": "3",
      "username": "leonard_cartify",
      "password": "123",
      "email": "leonard_cartify@gmail.com",
      "phone": "0902121",
      "isAdmin": false,
      "cart": [],
      "pendingOrders": [],
      "firstName": "",
      "middleName": "",
      "lastName": "",
      "birthDate": "2024-09-11",
      "interest": "",
      "status": "Active"
    },
    {
      "id": "4",
      "username": "pauline_cartify",
      "password": "123",
      "email": "pauline_cartify@gmail.com",
      "phone": "0902121",
      "isAdmin": false,
      "cart": [],
      "pendingOrders": [],
      "firstName": "",
      "middleName": "",
      "lastName": "",
      "birthDate": "2024-09-11",
      "interest": "",
      "status": "Active"
    },
    {
      "id": "5",
      "username": "admin_cartify",
      "password": "123",
      "email": "admin_cartify@email.com",
      "phone": "0902121",
      "isAdmin": true,
      "cart": [],
      "pendingOrders": [],
      "firstName": "admin",
      "middleName": "admin",
      "lastName": "admin",
      "birthDate": "2024-09-11",
      "interest": "",
      "status": "Active"
    }
  ],
  "products": [
    {
    }
  ]
}